Workbook

Sheet Assumptions
A1: Assumption | B1: Value
A2: Beds | B2: 300
A3: Occupancy | B3: 0.78
A4: Days per Year | B4: 365
A5: Revenue per Bed Day | B5: 1100
A6: Revenue Growth | B6: 0.03
A7: Operating Margin | B7: 0.18
A8: Debt Amount | B8: 140000000
A9: Debt Rate | B9: 0.0525
A10: Debt Term | B10: 25

Sheet Sources Used
A1: Sources | B1: Amount
A2: Debt | B2: 140000000
A3: Equity | B3: 60000000
A4: Total | B4: 200000000
A5: Uses | B5: Amount
A6: Construction | B6: 180000000
A7: Fees | B7: 10000000
A8: Contingency | B8: 10000000
A9: Total | B9: 200000000

Sheet Revenue
A1: Year | B1: Revenue
A2: 1 | B2: =Assumptions!B2*0.78*Assumptions!B4*Assumptions!B5 -> 93951000
A3: 2 | B3: =B2*1.03 -> 96769530
A4: 3 | B4: =B3*1.03 -> 99672616
A5: 4 | B5: =B4*1.03 -> 1.0266279e+08
A6: 5 | B6: =B5*1.03 -> 1.0574268e+08
A7: 6 | B7: =B6*1.03 -> 1.0891496e+08
A8: 7 | B8: =B7*1.03 -> 1.1218241e+08
A9: 8 | B9: =B8*1.03 -> 1.1554788e+08
A10: 9 | B10: =B9*1.03 -> 1.1901432e+08
A11: 10 | B11: =B10*1.03 -> 1.2258475e+08
A12: 11 | B12: =B11*1.03 -> 1.2626229e+08
A13: 12 | B13: =B12*1.03 -> 1.3005016e+08
A14: 13 | B14: =B13*1.03 -> 1.3395166e+08
... A26: 25 | B26: =B25*1.03 -> 1.9098304e+08

Sheet Operating Cost
A1: Year | B1: Revenue | C1: Expense | D1: EBITDA
A2: 1 | B2: =Assumptions!B2*0.78*Assumptions!B4*Assumptions!B5 -> 93951000 | C2: =B2-D2 -> 77039820 | D2: =B2*0.18 -> 16911180
A3: 2 | B3: =B2*1.03 -> 96769530 | C3: =B3-D3 -> 79351015 | D3: =B3*0.18 -> 17418515
A4: 3 | B4: =B3*1.03 -> 99672616 | C4: =B4-D4 -> 81731545 | D4: =B4*0.18 -> 17941071
A5: 4 | B5: =B4*1.03 -> 1.0266279e+08 | C5: =B5-D5 -> 84183491 | D5: =B5*0.18 -> 18479303
A6: 5 | B6: =B5*1.03 -> 1.0574268e+08 | C6: =B6-D6 -> 86708996 | D6: =B6*0.18 -> 19033682
A7: 6 | B7: =B6*1.03 -> 1.0891496e+08 | C7: =B7-D7 -> 89310266 | D7: =B7*0.18 -> 19604693
A8: 7 | B8: =B7*1.03 -> 1.1218241e+08 | C8: =B8-D8 -> 91989574 | D8: =B8*0.18 -> 20192833
A9: 8 | B9: =B8*1.03 -> 1.1554788e+08 | C9: =B9-D9 -> 94749261 | D9: =B9*0.18 -> 20798618
A10: 9 | B10: =B9*1.03 -> 1.1901432e+08 | C10: =B10-D10 -> 97591739 | D10: =B10*0.18 -> 21422577
A11: 10 | B11: =B10*1.03 -> 1.2258475e+08 | C11: =B11-D11 -> 1.0051949e+08 | D11: =B11*0.18 -> 22065254
A12: 11 | B12: =B11*1.03 -> 1.2626229e+08 | C12: =B12-D12 -> 1.0353508e+08 | D12: =B12*0.18 -> 22727212
A13: 12 | B13: =B12*1.03 -> 1.3005016e+08 | C13: =B13-D13 -> 1.0664113e+08 | D13: =B13*0.18 -> 23409028
A14: 13 | B14: =B13*1.03 -> 1.3395166e+08 | C14: =B14-D14 -> 1.0984036e+08 | D14: =B14*0.18 -> 24111299
... A26: 25 | B26: =B25*1.03 -> 1.9098304e+08 | C26: =B26-D26 -> 1.5660609e+08 | D26: =B26*0.18 -> 34376947

Sheet Cash Flow
A1: Year | B1: EBITDA | C1: CFADS
A2: 1 | B2: ='Operating Cost'!D2 -> 16911180 | C2: =B2 -> 16911180
A3: 2 | B3: ='Operating Cost'!D3 -> 17418515 | C3: =B3 -> 17418515
A4: 3 | B4: ='Operating Cost'!D4 -> 17941071 | C4: =B4 -> 17941071
A5: 4 | B5: ='Operating Cost'!D5 -> 18479303 | C5: =B5 -> 18479303
A6: 5 | B6: ='Operating Cost'!D6 -> 19033682 | C6: =B6 -> 19033682
A7: 6 | B7: ='Operating Cost'!D7 -> 19604693 | C7: =B7 -> 19604693
A8: 7 | B8: ='Operating Cost'!D8 -> 20192833 | C8: =B8 -> 20192833
A9: 8 | B9: ='Operating Cost'!D9 -> 20798618 | C9: =B9 -> 20798618
A10: 9 | B10: ='Operating Cost'!D10 -> 21422577 | C10: =B10 -> 21422577
A11: 10 | B11: ='Operating Cost'!D11 -> 22065254 | C11: =B11 -> 22065254
A12: 11 | B12: ='Operating Cost'!D12 -> 22727212 | C12: =B12 -> 22727212
A13: 12 | B13: ='Operating Cost'!D13 -> 23409028 | C13: =B13 -> 23409028
... A26: 25 | B26: ='Operating Cost'!D26 -> 34376947 | C26: =B26 -> 34376947

Sheet Debt Schedule
A1: Year | B1: Beginning Debt | C1: Principal | D1: Interest | E1: Ending Debt
A2: 1 | B2: =Assumptions!B8 -> 140000000 | C2: =B2/25 -> 5600000 | D2: =B2*0.0525 -> 7350000 | E2: =B2-C2 -> 134400000
A3: 2 | B3: =E2 -> 134400000 | C3: 5600000 | D3: =B3*0.0525 -> 7056000 | E3: =B3-C3 -> 128800000
A4: 3 | B4: =E3 -> 128800000 | C4: 5600000 | D4: =B4*0.0525 -> 6762000 | E4: =B4-C4 -> 123200000
A5: 4 | B5: =E4 -> 123200000 | C5: 5600000 | D5: =B5*0.0525 -> 6468000 | E5: =B5-C5 -> 117600000
A6: 5 | B6: =E5 -> 117600000 | C6: 5600000 | D6: =B6*0.0525 -> 6174000 | E6: =B6-C6 -> 112000000
A7: 6 | B7: =E6 -> 112000000 | C7: 5600000 | D7: =B7*0.0525 -> 5880000 | E7: =B7-C7 -> 106400000
A8: 7 | B8: =E7 -> 106400000 | C8: 5600000 | D8: =B8*0.0525 -> 5586000 | E8: =B8-C8 -> 100800000
A9: 8 | B9: =E8 -> 100800000 | C9: 5600000 | D9: =B9*0.0525 -> 5292000 | E9: =B9-C9 -> 95200000
A10: 9 | B10: =E9 -> 95200000 | C10: 5600000 | D10: =B10*0.0525 -> 4998000 | E10: =B10-C10 -> 89600000
A11: 10 | B11: =E10 -> 89600000 | C11: 5600000 | D11: =B11*0.0525 -> 4704000 | E11: =B11-C11 -> 84000000
A12: 11 | B12: =E11 -> 84000000 | C12: 5600000 | D12: =B12*0.0525 -> 4410000 | E12: =B12-C12 -> 78400000
A13: 12 | B13: =E12 -> 78400000 | C13: 5600000 | D13: =B13*0.0525 -> 4116000 | E13: =B13-C13 -> 72800000
A14: 13 | B14: =E13 -> 72800000 | C14: 5600000 | D14: =B14*0.0525 -> 3822000 | E14: =B14-C14 -> 67200000
... A26: 25 | B26: =E25 -> 5600000 | C26: 5600000 | D26: =B26*0.0525 -> 294000 | E26: =B26-C26 -> 0

Sheet DSCR
A1: Year | B1: DSCR | C1: CFADS | D1: Debt Services
A2: 1 | B2: ='Debt Schedule'!C2+'Debt Schedule'!D2 -> 12950000 | C2: ='Cash Flow'!C2 -> 16911180 | D2: =C2/B2 -> 1.3058826
A3: 2 | B3: ='Debt Schedule'!C3+'Debt Schedule'!D3 -> 12656000 | C3: ='Cash Flow'!C3 -> 17418515 | D3: =C3/B3 -> 1.3763049
A4: 3 | B4: ='Debt Schedule'!C4+'Debt Schedule'!D4 -> 12362000 | C4: ='Cash Flow'!C4 -> 17941071 | D4: =C4/B4 -> 1.4513081
A5: 4 | B5: ='Debt Schedule'!C5+'Debt Schedule'!D5 -> 12068000 | C5: ='Cash Flow'!C5 -> 18479303 | D5: =C5/B5 -> 1.5312647
A6: 5 | B6: ='Debt Schedule'!C6+'Debt Schedule'!D6 -> 11774000 | C6: ='Cash Flow'!C6 -> 19033682 | D6: =C6/B6 -> 1.6165859
A7: 6 | B7: ='Debt Schedule'!C7+'Debt Schedule'!D7 -> 11480000 | C7: ='Cash Flow'!C7 -> 19604693 | D7: =C7/B7 -> 1.7077258
A8: 7 | B8: ='Debt Schedule'!C8+'Debt Schedule'!D8 -> 11186000 | C8: ='Cash Flow'!C8 -> 20192833 | D8: =C8/B8 -> 1.805188
A9: 8 | B9: ='Debt Schedule'!C9+'Debt Schedule'!D9 -> 10892000 | C9: ='Cash Flow'!C9 -> 20798618 | D9: =C9/B9 -> 1.9095316
A10: 9 | B10: ='Debt Schedule'!C10+'Debt Schedule'!D10 -> 10598000 | C10: ='Cash Flow'!C10 -> 21422577 | D10: =C10/B10 -> 2.0213792
A11: 10 | B11: ='Debt Schedule'!C11+'Debt Schedule'!D11 -> 10304000 | C11: ='Cash Flow'!C11 -> 22065254 | D11: =C11/B11 -> 2.1414261
A12: 11 | B12: ='Debt Schedule'!C12+'Debt Schedule'!D12 -> 10010000 | C12: ='Cash Flow'!C12 -> 22727212 | D12: =C12/B12 -> 2.2704507
A13: 12 | B13: ='Debt Schedule'!C13+'Debt Schedule'!D13 -> 9716000 | C13: ='Cash Flow'!C13 -> 23409028 | D13: =C13/B13 -> 2.4093277
... A26: 25 | B26: ='Debt Schedule'!C26+'Debt Schedule'!D26 -> 5894000 | C26: ='Cash Flow'!C26 -> 34376947 | D26: =C26/B26 -> 5.8325326

Sheet Scenarios 
A1: Assumption | B1: Downside | C1: Base | D1: Upside | F1: Selected Scenario | G1: Selected Assumptiosn
A2: Occupancy | B2: 0.65 | C2: 0.78 | D2: 0.85 | F2: Base | G2: Occupancy | H2: =IF($F$2="Downside",B2, IF($F$2="Base",C2,D2)) -> 0.78
A3: Revenue Growth | B3: 0.01 | C3: 0.03 | D3: 0.05 | G3: Revenue Growth | H3: =IF($F$2="Downside",B3, IF($F$2="Base",C3,D3)) -> 0.03
A4: Operating Margin | B4: 0.15 | C4: 0.18 | D4: 0.2 | G4: Operating Margin
